hello_robot_stretch_body_tools_dev-0.3.0.data/scripts/stretch_about.py
hello_robot_stretch_body_tools_dev-0.3.0.data/scripts/stretch_about_text.py
hello_robot_stretch_body_tools_dev-0.3.0.data/scripts/stretch_arm_home.py
hello_robot_stretch_body_tools_dev-0.3.0.data/scripts/stretch_arm_jog.py
hello_robot_stretch_body_tools_dev-0.3.0.data/scripts/stretch_audio_test.py
hello_robot_stretch_body_tools_dev-0.3.0.data/scripts/stretch_base_jog.py
hello_robot_stretch_body_tools_dev-0.3.0.data/scripts/stretch_gripper_home.py
hello_robot_stretch_body_tools_dev-0.3.0.data/scripts/stretch_gripper_jog.py
hello_robot_stretch_body_tools_dev-0.3.0.data/scripts/stretch_hardware_echo.py
hello_robot_stretch_body_tools_dev-0.3.0.data/scripts/stretch_head_jog.py
hello_robot_stretch_body_tools_dev-0.3.0.data/scripts/stretch_lift_home.py
hello_robot_stretch_body_tools_dev-0.3.0.data/scripts/stretch_lift_jog.py
hello_robot_stretch_body_tools_dev-0.3.0.data/scripts/stretch_params.py
hello_robot_stretch_body_tools_dev-0.3.0.data/scripts/stretch_pimu_jog.py
hello_robot_stretch_body_tools_dev-0.3.0.data/scripts/stretch_pimu_scope.py
hello_robot_stretch_body_tools_dev-0.3.0.data/scripts/stretch_realsense_visualizer.py
hello_robot_stretch_body_tools_dev-0.3.0.data/scripts/stretch_respeaker_test.py
hello_robot_stretch_body_tools_dev-0.3.0.data/scripts/stretch_robot_battery_check.py
hello_robot_stretch_body_tools_dev-0.3.0.data/scripts/stretch_robot_dynamixel_reboot.py
hello_robot_stretch_body_tools_dev-0.3.0.data/scripts/stretch_robot_home.py
hello_robot_stretch_body_tools_dev-0.3.0.data/scripts/stretch_robot_jog.py
hello_robot_stretch_body_tools_dev-0.3.0.data/scripts/stretch_robot_keyboard_teleop.py
hello_robot_stretch_body_tools_dev-0.3.0.data/scripts/stretch_robot_monitor.py
hello_robot_stretch_body_tools_dev-0.3.0.data/scripts/stretch_robot_stow.py
hello_robot_stretch_body_tools_dev-0.3.0.data/scripts/stretch_robot_system_check.py
hello_robot_stretch_body_tools_dev-0.3.0.dist-info/DESCRIPTION.rst
hello_robot_stretch_body_tools_dev-0.3.0.dist-info/METADATA
hello_robot_stretch_body_tools_dev-0.3.0.dist-info/RECORD
hello_robot_stretch_body_tools_dev-0.3.0.dist-info/WHEEL
hello_robot_stretch_body_tools_dev-0.3.0.dist-info/metadata.json
hello_robot_stretch_body_tools_dev-0.3.0.dist-info/top_level.txt
