Metadata-Version: 2.0
Name: hello-robot-stretch-body-tools-dev
Version: 0.3.0
Summary: Stretch Body Tools
Home-page: https://github.com/hello-robot/stretch_body
Author: Hello Robot Inc
Author-email: support@hello-robot.com
License: UNKNOWN
Platform: UNKNOWN
Classifier: Programming Language :: Python :: 3
Classifier: Operating System :: OS Independent
Classifier: License :: OSI Approved :: Apache Software License
Requires-Dist: numpy
Requires-Dist: scipy
Requires-Dist: matplotlib
Requires-Dist: ipython
Requires-Dist: pandas
Requires-Dist: sympy
Requires-Dist: nose
Requires-Dist: inputs
Requires-Dist: drawnow
Requires-Dist: rplidar-roboticia
Requires-Dist: snakeviz
Requires-Dist: pyusb
Requires-Dist: SpeechRecognition
Requires-Dist: pixel-ring
Requires-Dist: click
Requires-Dist: cma
Requires-Dist: opencv-contrib-python
Requires-Dist: colorama
Requires-Dist: scikit-image
Requires-Dist: open3d
Requires-Dist: pyrealsense2
Requires-Dist: trimesh (==3.6.38)
Requires-Dist: urdfpy
Requires-Dist: pyyaml (>=5.1)
Requires-Dist: hello-robot-stretch-body
Requires-Dist: pyglet (==1.4.10); python_version < "3.0"
